donate_a_pytest/__init__.py
donate_a_pytest/decorators.py
donate_a_pytest/generators.py
donate_a_pytest/interface.py
donate_a_pytest/main.py
donate_a_pytest/model.py
donate_a_pytest/plugin.py
donate_a_pytest/tests_crawler.py
donate_a_pytest/utils.py
donate_a_pytest-0.1.7.dist-info/METADATA
donate_a_pytest-0.1.7.dist-info/WHEEL
donate_a_pytest-0.1.7.dist-info/entry_points.txt
donate_a_pytest-0.1.7.dist-info/RECORD
