Metadata-Version: 2.3
Name: donate-a-pytest
Version: 0.1.7
Summary: A pytest extension for sharing test cases
License: MIT
Keywords: pytest,testing,test-cases,sharing-tests
Author: Trung Pham
Author-email: trungphamquoc@outlook.com
Requires-Python: >=3.10
Classifier: Development Status :: 4 - Beta
Classifier: Framework :: Pytest
Classifier: Intended Audience :: Developers
Classifier: License :: OSI Approved :: MIT License
Classifier: Programming Language :: Python :: 3
Classifier: Programming Language :: Python :: 3.10
Classifier: Programming Language :: Python :: 3.11
Classifier: Topic :: Software Development :: Testing
Classifier: Topic :: Software Development :: Libraries :: Python Modules
Requires-Dist: pydantic (>=2.11.2,<3.0.0)
Requires-Dist: pytest (>=8.3.5,<9.0.0)
Requires-Dist: pyyaml (>=6.0.2,<7.0.0)
Requires-Dist: tqdm (>=4.67.1,<5.0.0)
Project-URL: Bug Tracker, https://github.com/yourusername/donate-a-pytest/issues
Project-URL: Documentation, https://github.com/yourusername/donate-a-pytest#readme
Project-URL: Homepage, https://github.com/yourusername/donate-a-pytest
